Workbook

Sheet Info_Schedule
B19: Corso | C19: A05003 Corporate finance e M&A
B20: Matricola | C20: 34226
B21: Nome | C21: BRYAN
B22: Cognome | C22: LATTUADA
B23: Assigment_n | C23: 3*

Sheet sensitivity_analysis
B3: Sensitive Analysis | C3: Historical Data | F3: Forecast Data
A4: x | B4: Voce (€ milioni) | C4: 2020 | D4: =+C4+1 -> 2021 | E4: =+D4+1 -> 2022 | F4: =+E4+1 -> 2023 | G4: =+F4+1 -> 2024 | H4: =+G4+1 -> 2025
A6: x | B6: Dashboard KPI's
B8: Live | C8: EV | D8: =+EV_EqV!F15 -> 16300.189 | F8: leggenda: | G8: 1 | H8: Base
B9: 1 | C9: EqV | D9: =+EV_EqV!F20 -> 16350.189 | G9: 2 | H9: Upside
G10: 3 | H10: Downside
B11: KPI area
B12: Profitability | C12: =+C59 -> 0.207 | D12: =+D59 -> 0.24338225 | E12: =+E59 -> 0.28225998 | F12: =+F59 -> 0.32116869 | G12: =+G59 -> 0.30812423 | H12: =+H59 -> 0.33382148
B13: Credit Risk | C13: =+C74 -> 0.048309179 | D13: =+D74 -> 0.80597199 | E13: =+E74 -> 1.7251274 | F13: =+F74 -> 1.3504172 | G13: =+G74 -> 0.61804675 | H13: =+H74 -> 0.25094527
B14: Liquidity | C14: =+C89 -> 0 | D14: =+D89 -> -0.77746267 | E14: =+E89 -> -1.066606 | F14: =+F89 -> 0.036440627 | G14: =+G89 -> 0.84229105 | H14: =+H89 -> 0.81300069
B15: Valuation (EBITDAx) | C15: =+C106 -> 0 | D15: =+D106 -> 0 | E15: =+E106 -> 0 | F15: =+F106 -> 0 | G15: =+G106 -> 0 | H15: =+H106 -> 15.748975
B16: ROIC | C16: =+C110 -> 0 | D16: =+D110 -> 0.15772919 | E16: =+E110 -> 0.12901118 | F16: =+F110 -> 0.14849529 | G16: =+G110 -> 0.14457558 | H16: =+H110 -> 0.1926718
A19: x | B19: Data Visualitation
A55: x | B55: Indici di Redditività
B57: Revenues | C57: =+'3_statement_model'!C71 -> 5000 | D57: =+'3_statement_model'!D73 -> 5764.8 | E57: =+'3_statement_model'!E73 -> 6567.984 | F57: =+'3_statement_model'!F73 -> 7483.3027 | G57: =+'3_statement_model'!G73 -> 7413.0047 | H57: =+'3_statement_model'!H73 -> 8003.6642
B58: EBITDA | C58: =+'3_statement_model'!C82 -> 1035 | D58: =+'3_statement_model'!D82 -> 1403.05 | E58: =+'3_statement_model'!E82 -> 1853.879 | F58: =+'3_statement_model'!F82 -> 2403.4025 | G58: =+'3_statement_model'!G82 -> 2284.1263 | H58: =+'3_statement_model'!H82 -> 2671.795
B59: EBITDA% | C59: =+C58/C57 -> 0.207 | D59: =+D58/D57 -> 0.24338225 | E59: =+E58/E57 -> 0.28225998 | F59: =+F58/F57 -> 0.32116869 | G59: =+G58/G57 -> 0.30812423 | H59: =+H58/H57 -> 0.33382148
B61: Revenues | C61: =+C57 -> 5000 | D61: =+'3_statement_model'!D73 -> 5764.8 | E61: =+'3_statement_model'!E73 -> 6567.984 | F61: =+'3_statement_model'!F73 -> 7483.3027 | G61: =+'3_statement_model'!G73 -> 7413.0047 | H61: =+'3_statement_model'!H73 -> 8003.6642
B62: EBIT | C62: =+'3_statement_model'!C88 -> 655 | D62: =+'3_statement_model'!D88 -> 985.05 | E62: =+'3_statement_model'!E88 -> 1394.079 | F62: =+'3_statement_model'!F88 -> 1851.6425 | G62: =+'3_statement_model'!G88 -> 1622.0143 | H62: =+'3_statement_model'!H88 -> 1877.2606
B63: EBIT% | C63: =+C62/C61 -> 0.131 | D63: =+D62/D61 -> 0.17087323 | E63: =+E62/E61 -> 0.21225371 | F63: =+F62/F61 -> 0.24743654 | G63: =+G62/G61 -> 0.2188066 | H63: =+H62/H61 -> 0.23455015
B65: Revenues | C65: =+C57 -> 5000 | D65: =+'3_statement_model'!D73 -> 5764.8 | E65: =+'3_statement_model'!E73 -> 6567.984 | F65: =+'3_statement_model'!F73 -> 7483.3027 | G65: =+'3_statement_model'!G73 -> 7413.0047 | H65: =+'3_statement_model'!H73 -> 8003.6642
B66: Net Revenues | C66: =+'3_statement_model'!C97 -> 375.1 | D66: =+'3_statement_model'!D97 -> 554.931 | E66: =+'3_statement_model'!E97 -> 808.52898 | F66: =+'3_statement_model'!F97 -> 1064.3184 | G66: =+'3_statement_model'!G97 -> 949.84889 | H66: =+'3_statement_model'!H97 -> 1108.1016
B67: Net Revenues% | C67: =+C66/C65 -> 0.07502 | D67: =+D66/D65 -> 0.096261969 | E67: =+E66/E65 -> 0.12310155 | F67: =+F66/F65 -> 0.14222575 | G67: =+G66/G65 -> 0.12813278 | H67: =+H66/H65 -> 0.13844928
A70: x | B70: Indici di sostenibilità
B72: PFN | C72: =+ABS(+'3_statement_model'!C113-'3_statement_model'!C103) -> 50 | D72: =+ABS(+'3_statement_model'!D113-'3_statement_model'!D103) -> 1130.819 | E72: =+ABS(+'3_statement_model'!E113-'3_statement_model'!E103) -> 3198.1775 | F72: =+ABS(+'3_statement_model'!F113-'3_statement_model'!F103) -> 3245.596 | G72: =+ABS(+'3_statement_model'!G113-'3_statement_model'!G103) -> 1411.6969 | H72: =+ABS(+'3_statement_model'!H113-'3_statement_model'!H103) -> 670.47431
B73: EBITDA | C73: =+C58 -> 1035 | D73: =+D58 -> 1403.05 | E73: =+E58 -> 1853.879 | F73: =+F58 -> 2403.4025 | G73: =+G58 -> 2284.1263 | H73: =+H58 -> 2671.795
B74: Net Debt/EBITA | C74: =+C72/C73 -> 0.048309179 | D74: =+D72/D73 -> 0.80597199 | E74: =+E72/E73 -> 1.7251274 | F74: =+F72/F73 -> 1.3504172 | G74: =+G72/G73 -> 0.61804675 | H74: =+H72/H73 -> 0.25094527
B76: Net Debt
B77: Equity
B78: Leverage (Fixed data) | C78: 0.6
B80: Debt Service Coverage Ratio
B81: EBITDA | C81: =+C58 -> 1035 | D81: =+D73 -> 1403.05 | E81: =+E73 -> 1853.879 | F81: =+F73 -> 2403.4025 | G81: =+G73 -> 2284.1263 | H81: =+H73 -> 2671.795
B82: Oneri Finanziari | C82: =+'3_statement_model'!C91 -> 70 | D82: =+'3_statement_model'!D91 -> 120 | E82: =+'3_statement_model'!E91 -> 120 | F82: =+'3_statement_model'!F91 -> 120 | G82: =+'3_statement_model'!G91 -> 120 | H82: =+'3_statement_model'!H91 -> 120
C83: =+C81/C82 -> 14.785714 | D83: =+D81/D82 -> 11.692083 | E83: =+E81/E82 -> 15.448992 | F83: =+F81/F82 -> 20.028354 | G83: =+G81/G82 -> 19.034386 | H83: =+H81/H82 -> 22.264958
A85: x | B85: Metriche di Efficienza del Capitale e Liquidità
B87: Operating Income (FCFF) | C87: =+'3_statement_model'!C135 -> 0 | D87: =+'3_statement_model'!D135 -> -1090.819 | E87: =+'3_statement_model'!E135 -> -1977.3585 | F87: =+'3_statement_model'!F135 -> 87.581495 | G87: =+'3_statement_model'!G135 -> 1923.8992 | H87: =+'3_statement_model'!H135 -> 2172.1712
B88: EBITDA | C88: =+C58 -> 1035 | D88: =+D58 -> 1403.05 | E88: =+E58 -> 1853.879 | F88: =+F58 -> 2403.4025 | G88: =+G58 -> 2284.1263 | H88: =+H58 -> 2671.795
B89: Cash Conversion Rate | C89: =+C87/C88 -> 0 | D89: =+D87/D88 -> -0.77746267 | E89: =+E87/E88 -> -1.066606 | F89: =+F87/F88 -> 0.036440627 | G89: =+G87/G88 -> 0.84229105 | H89: =+H87/H88 -> 0.81300069
B91: CapEx | D91: =+'3_statement_model'!D163 -> 1785 | E91: =+'3_statement_model'!E163 -> 3123.5 | F91: =+'3_statement_model'!F163 -> 1508.2 | G91: =+'3_statement_model'!G163 -> -0.028 | H91: =+'3_statement_model'!H163 -> -0.1136
B92: Revenues | C92: =+C57 -> 5000 | D92: =+D57 -> 5764.8 | E92: =+E57 -> 6567.984 | F92: =+F57 -> 7483.3027 | G92: =+G57 -> 7413.0047 | H92: =+H57 -> 8003.6642
B93: Investment Efficient | C93: 0 | D93: =+D91/D92 -> 0.3096378 | E93: =+E91/E92 -> 0.4755645 | F93: =+F91/F92 -> 0.20154203 | G93: =+G91/G92 -> -3.7771459e-06 | H93: =+H91/H92 -> -1.4193499e-05
B96: NWC Efficiency
A98: x | B98: Metriche di Rendimento e Valutazione
B100: WACC | H100: =+EV_EqV!C42 -> 0.0735875
B102: EVA | H102: =+'3_statement_model'!H127-(H109*H100) -> 740.50841
B104: Enterprise Value | H104: =+EV_EqV!F15 -> 16300.189
B105: EBITDA | H105: =+C58 -> 1035
B106: xEV/EBITDA | H106: =+H104/H105 -> 15.748975
B108: NOPAT | C108: =+'3_statement_model'!C127 -> 0 | D108: =+'3_statement_model'!D127 -> 644.931 | E108: =+'3_statement_model'!E127 -> 898.52898 | F108: =+'3_statement_model'!F127 -> 1199.3184 | G108: =+'3_statement_model'!G127 -> 1039.8489 | H108: =+'3_statement_model'!H127 -> 1198.1016
B109: Capitale Investito netto (D+E) | C109: =+'3_statement_model'!C119+('3_statement_model'!C113-'3_statement_model'!C103) -> 2353.1 | D109: =+'3_statement_model'!D119+('3_statement_model'!D113-'3_statement_model'!D103) -> 4088.85 | E109: =+'3_statement_model'!E119+('3_statement_model'!E113-'3_statement_model'!E103) -> 6964.7375 | F109: =+'3_statement_model'!F119+('3_statement_model'!F113-'3_statement_model'!F103) -> 8076.4744 | G109: =+'3_statement_model'!G119+('3_statement_model'!G113-'3_statement_model'!G103) -> 7192.4241 | H109: =+'3_statement_model'!H119+('3_statement_model'!H113-'3_statement_model'!H103) -> 6218.3545
B110: ROIC | C110: =+C108/C109 -> 0 | D110: =+D108/D109 -> 0.15772919 | E110: =+E108/E109 -> 0.12901118 | F110: =+F108/F109 -> 0.14849529 | G110: =+G108/G109 -> 0.14457558 | H110: =+H108/H109 -> 0.1926718
B111: Check | C111: =+IF(C110>$H$100, "Profit", "Loss") -> Loss | D111: =+IF(D110>$H$100, "Profit", "Loss") -> Profit | E111: =+IF(E110>$H$100, "Profit", "Loss") -> Profit | F111: =+IF(F110>$H$100, "Profit", "Loss") -> Profit | G111: =+IF(G110>$H$100, "Profit", "Loss") -> Profit | H111: =+IF(H110>$H$100, "Profit", "Loss") -> Profit

Sheet 3_statement_model
F3: Forecast Periods
A4: x | B4: Voce (€ milioni) | C4: 2020 | D4: =+C4+1 -> 2021 | E4: =+D4+1 -> 2022 | F4: =+E4+1 -> 2023 | G4: =+F4+1 -> 2024 | H4: =+G4+1 -> 2025
A6: x | B6: Assumptions
A8: x | B8: Live Case
B9: revenues | D9: =+CHOOSE(sensitivity_analysis!$B$9,'3_statement_model'!D24,'3_statement_model'!D39,'3_statement_model'!D54) -> 0.14 | E9: =+CHOOSE(sensitivity_analysis!$B$9,'3_statement_model'!E24,'3_statement_model'!E39,'3_statement_model'!E54) -> 0.14 | F9: =+CHOOSE(sensitivity_analysis!$B$9,'3_statement_model'!F24,'3_statement_model'!F39,'3_statement_model'!F54) -> 0.14 | G9: =+CHOOSE(sensitivity_analysis!$B$9,'3_statement_model'!G24,'3_statement_model'!G39,'3_statement_model'!G54) -> -0.01 | H9: =+CHOOSE(sensitivity_analysis!$B$9,'3_statement_model'!H24,'3_statement_model'!H39,'3_statement_model'!H54) -> 0.08
B10: other incomes | D10: =+CHOOSE(sensitivity_analysis!$B$9,'3_statement_model'!D25,'3_statement_model'!D40,'3_statement_model'!D55) -> 0.08 | E10: =+CHOOSE(sensitivity_analysis!$B$9,'3_statement_model'!E25,'3_statement_model'!E40,'3_statement_model'!E55) -> 0.08 | F10: =+CHOOSE(sensitivity_analysis!$B$9,'3_statement_model'!F25,'3_statement_model'!F40,'3_statement_model'!F55) -> 0.08 | G10: =+CHOOSE(sensitivity_analysis!$B$9,'3_statement_model'!G25,'3_statement_model'!G40,'3_statement_model'!G55) -> 0.05 | H10: =+CHOOSE(sensitivity_analysis!$B$9,'3_statement_model'!H25,'3_statement_model'!H40,'3_statement_model'!H55) -> 0.05
B11: COGS | D11: =+CHOOSE(sensitivity_analysis!$B$9,'3_statement_model'!D26,'3_statement_model'!D41,'3_statement_model'!D56) -> 0.12 | E11: =+CHOOSE(sensitivity_analysis!$B$9,'3_statement_model'!E26,'3_statement_model'!E41,'3_statement_model'!E56) -> 0.11 | F11: =+CHOOSE(sensitivity_analysis!$B$9,'3_statement_model'!F26,'3_statement_model'!F41,'3_statement_model'!F56) -> 0.1 | G11: =+CHOOSE(sensitivity_analysis!$B$9,'3_statement_model'!G26,'3_statement_model'!G41,'3_statement_model'!G56) -> -0.03 | H11: =+CHOOSE(sensitivity_analysis!$B$9,'3_statement_model'!H26,'3_statement_model'!H41,'3_statement_model'!H56) -> 0.05
B12: salari | D12: =+CHOOSE(sensitivity_analysis!$B$9,'3_statement_model'!D27,'3_statement_model'!D42,'3_statement_model'!D57) -> 0.07 | E12: =+CHOOSE(sensitivity_analysis!$B$9,'3_statement_model'!E27,'3_statement_model'!E42,'3_statement_model'!E57) -> 0.07 | F12: =+CHOOSE(sensitivity_analysis!$B$9,'3_statement_model'!F27,'3_statement_model'!F42,'3_statement_model'!F57) -> 0.07 | G12: =+CHOOSE(sensitivity_analysis!$B$9,'3_statement_model'!G27,'3_statement_model'!G42,'3_statement_model'!G57) -> 0.03 | H12: =+CHOOSE(sensitivity_analysis!$B$9,'3_statement_model'!H27,'3_statement_model'!H42,'3_statement_model'!H57) -> 0.03
B13: oneri sociali | D13: =+CHOOSE(sensitivity_analysis!$B$9,'3_statement_model'!D28,'3_statement_model'!D43,'3_statement_model'!D58) -> 0.045 | E13: =+CHOOSE(sensitivity_analysis!$B$9,'3_statement_model'!E28,'3_statement_model'!E43,'3_statement_model'!E58) -> 0.045 | F13: =+CHOOSE(sensitivity_analysis!$B$9,'3_statement_model'!F28,'3_statement_model'!F43,'3_statement_model'!F58) -> 0.045 | G13: =+CHOOSE(sensitivity_analysis!$B$9,'3_statement_model'!G28,'3_statement_model'!G43,'3_statement_model'!G58) -> 0.045 | H13: =+CHOOSE(sensitivity_analysis!$B$9,'3_statement_model'!H28,'3_statement_model'!H43,'3_statement_model'!H58) -> 0.045
B14: accantonamento TFR | D14: =+CHOOSE(sensitivity_analysis!$B$9,'3_statement_model'!D29,'3_statement_model'!D44,'3_statement_model'!D59) -> 0.05 | E14: =+CHOOSE(sensitivity_analysis!$B$9,'3_statement_model'!E29,'3_statement_model'!E44,'3_statement_model'!E59) -> 0.05 | F14: =+CHOOSE(sensitivity_analysis!$B$9,'3_statement_model'!F29,'3_statement_model'!F44,'3_statement_model'!F59) -> 0.05 | G14: =+CHOOSE(sensitivity_analysis!$B$9,'3_statement_model'!G29,'3_statement_model'!G44,'3_statement_model'!G59) -> 0.05 | H14: =+CHOOSE(sensitivity_analysis!$B$9,'3_statement_model'!H29,'3_statement_model'!H44,'3_statement_model'!H59) -> 0.05
B15: tangibles assets | D15: =+CHOOSE(sensitivity_analysis!$B$9,'3_statement_model'!D30,'3_statement_model'!D45,'3_statement_model'!D60) -> 0.1 | E15: =+CHOOSE(sensitivity_analysis!$B$9,'3_statement_model'!E30,'3_statement_model'!E45,'3_statement_model'!E60) -> 0.1 | F15: =+CHOOSE(sensitivity_analysis!$B$9,'3_statement_model'!F30,'3_statement_model'!F45,'3_statement_model'!F60) -> 0.2 | G15: =+CHOOSE(sensitivity_analysis!$B$9,'3_statement_model'!G30,'3_statement_model'!G45,'3_statement_model'!G60) -> 0.2 | H15: =+CHOOSE(sensitivity_analysis!$B$9,'3_statement_model'!H30,'3_statement_model'!H45,'3_statement_model'!H60) -> 0.2
B16: intangibles assets | D16: =+CHOOSE(sensitivity_analysis!$B$9,'3_statement_model'!D31,'3_statement_model'!D46,'3_statement_model'!D61) -> 0.1 | E16: =+CHOOSE(sensitivity_analysis!$B$9,'3_statement_model'!E31,'3_statement_model'!E46,'3_statement_model'!E61) -> 0.1 | F16: =+CHOOSE(sensitivity_analysis!$B$9,'3_statement_model'!F31,'3_statement_model'!F46,'3_statement_model'!F61) -> 0.2 | G16: =+CHOOSE(sensitivity_analysis!$B$9,'3_statement_model'!G31,'3_statement_model'!G46,'3_statement_model'!G61) -> 0.2 | H16: =+CHOOSE(sensitivity_analysis!$B$9,'3_statement_model'!H31,'3_statement_model'!H46,'3_statement_model'!H61) -> 0.2
B17: proventi finanziari | D17: =+CHOOSE(sensitivity_analysis!$B$9,'3_statement_model'!D32,'3_statement_model'!D47,'3_statement_model'!D62) -> 30 | E17: =+CHOOSE(sensitivity_analysis!$B$9,'3_statement_model'!E32,'3_statement_model'!E47,'3_statement_model'!E62) -> 30 | F17: =+CHOOSE(sensitivity_analysis!$B$9,'3_statement_model'!F32,'3_statement_model'!F47,'3_statement_model'!F62) -> 30 | G17: =+CHOOSE(sensitivity_analysis!$B$9,'3_statement_model'!G32,'3_statement_model'!G47,'3_statement_model'!G62) -> 30 | H17: =+CHOOSE(sensitivity_analysis!$B$9,'3_statement_model'!H32,'3_statement_model'!H47,'3_statement_model'!H62) -> 30
B18: oneri finanziari | D18: =+CHOOSE(sensitivity_analysis!$B$9,'3_statement_model'!D33,'3_statement_model'!D48,'3_statement_model'!D63) -> 120 | E18: =+CHOOSE(sensitivity_analysis!$B$9,'3_statement_model'!E33,'3_statement_model'!E48,'3_statement_model'!E63) -> 120 | F18: =+CHOOSE(sensitivity_analysis!$B$9,'3_statement_model'!F33,'3_statement_model'!F48,'3_statement_model'!F63) -> 120 | G18: =+CHOOSE(sensitivity_analysis!$B$9,'3_statement_model'!G33,'3_statement_model'!G48,'3_statement_model'!G63) -> 120 | H18: =+CHOOSE(sensitivity_analysis!$B$9,'3_statement_model'!H33,'3_statement_model'!H48,'3_statement_model'!H63) -> 120
B19: oneri gestione straordinaria | D19: =+CHOOSE(sensitivity_analysis!$B$9,'3_statement_model'!D34,'3_statement_model'!D49,'3_statement_model'!D64) -> 0 | E19: =+CHOOSE(sensitivity_analysis!$B$9,'3_statement_model'!E34,'3_statement_model'!E49,'3_statement_model'!E64) -> 0 | F19: =+CHOOSE(sensitivity_analysis!$B$9,'3_statement_model'!F34,'3_statement_model'!F49,'3_statement_model'!F64) -> -45 | G19: =+CHOOSE(sensitivity_analysis!$B$9,'3_statement_model'!G34,'3_statement_model'!G49,'3_statement_model'!G64) -> 0 | H19: =+CHOOSE(sensitivity_analysis!$B$9,'3_statement_model'!H34,'3_statement_model'!H49,'3_statement_model'!H64) -> 0
B20: tax rate | C20: 0.38 | D20: =+CHOOSE(sensitivity_analysis!$B$9,'3_statement_model'!D35,'3_statement_model'!D50,'3_statement_model'!D65) -> 0.38 | E20: =+CHOOSE(sensitivity_analysis!$B$9,'3_statement_model'!E35,'3_statement_model'!E50,'3_statement_model'!E65) -> 0.38 | F20: =+CHOOSE(sensitivity_analysis!$B$9,'3_statement_model'!F35,'3_statement_model'!F50,'3_statement_model'!F65) -> 0.38 | G20: =+CHOOSE(sensitivity_analysis!$B$9,'3_statement_model'!G35,'3_statement_model'!G50,'3_statement_model'!G65) -> 0.38 | H20: =+CHOOSE(sensitivity_analysis!$B$9,'3_statement_model'!H35,'3_statement_model'!H50,'3_statement_model'!H65) -> 0.38
B21: liquidazione TFR | D21: =+CHOOSE(sensitivity_analysis!$B$9,'3_statement_model'!D36,'3_statement_model'!D51,'3_statement_model'!D66) -> 0 | E21: =+CHOOSE(sensitivity_analysis!$B$9,'3_statement_model'!E36,'3_statement_model'!E51,'3_statement_model'!E66) -> 0 | F21: =+CHOOSE(sensitivity_analysis!$B$9,'3_statement_model'!F36,'3_statement_model'!F51,'3_statement_model'!F66) -> 0 | G21: =+CHOOSE(sensitivity_analysis!$B$9,'3_statement_model'!G36,'3_statement_model'!G51,'3_statement_model'!G66) -> -30 | H21: =+CHOOSE(sensitivity_analysis!$B$9,'3_statement_model'!H36,'3_statement_model'!H51,'3_statement_model'!H66) -> -30
A23: x | B23: Base Case
B24: revenues | D24: 0.14 | E24: 0.14 | F24: 0.14 | G24: -0.01 | H24: 0.08
B25: other incomes | D25: 0.08 | E25: 0.08 | F25: 0.08 | G25: 0.05 | H25: 0.05
B26: COGS | D26: 0.12 | E26: 0.11 | F26: 0.1 | G26: -0.03 | H26: 0.05
B27: salari | D27: 0.07 | E27: 0.07 | F27: 0.07 | G27: 0.03 | H27: 0.03
B28: oenri sociali | D28: 0.045 | E28: 0.045 | F28: 0.045 | G28: 0.045 | H28: 0.045
B29: accantonamento TFR | D29: 0.05 | E29: 0.05 | F29: 0.05 | G29: 0.05 | H29: 0.05
B30: tangibles assets | D30: 0.1 | E30: 0.1 | F30: 0.2 | G30: 0.2 | H30: 0.2
B31: itangibles assets | D31: 0.1 | E31: 0.1 | F31: 0.2 | G31: 0.2 | H31: 0.2
B32: proventi finanziari | D32: 30 | E32: 30 | F32: 30 | G32: 30 | H32: 30
B33: oneri finanziari | D33: 120 | E33: 120 | F33: 120 | G33: 120 | H33: 120
B34: oneri gestione straordinaria | F34: -45
B35: tax rate | C35: 0.38 | D35: 0.38 | E35: 0.38 | F35: 0.38 | G35: 0.38 | H35: 0.38
B36: liquidazione TFR | G36: -30 | H36: -30
A38: x | B38: Upside Case
B39: revenues | D39: 0.14 | E39: 0.15 | F39: 0.145 | G39: 0.06 | H39: 0.12
B40: other incomes | D40: 0.08 | E40: 0.08 | F40: 0.08 | G40: 0.05 | H40: 0.05
B41: COGS | D41: 0.12 | E41: 0.11 | F41: 0.1 | G41: -0.03 | H41: 0.05
B42: salari | D42: 0.07 | E42: 0.07 | F42: 0.07 | G42: 0.03 | H42: 0.03
B43: oenri sociali | D43: 0.045 | E43: 0.045 | F43: 0.045 | G43: 0.045 | H43: 0.045
B44: accantonamento TFR | D44: 0.05 | E44: 0.05 | F44: 0.05 | G44: 0.05 | H44: 0.05
B45: tangibles assets | D45: 0.1 | E45: 0.1 | F45: 0.2 | G45: 0.2 | H45: 0.2
B46: itangibles assets | D46: 0.1 | E46: 0.1 | F46: 0.2 | G46: 0.2 | H46: 0.2
B47: proventi finanziari | D47: 30 | E47: 30 | F47: 30 | G47: 30 | H47: 30
B48: oneri finanziari | D48: =+D33 -> 120 | E48: =+E33 -> 120 | F48: =+F33 -> 120 | G48: =+G33 -> 120 | H48: =+H33 -> 120
B49: oneri gestione straordinaria | F49: -45
B50: tax rate | C50: =+C35 -> 0.38 | D50: =+D35 -> 0.38 | E50: =+E35 -> 0.38 | F50: =+F35 -> 0.38 | G50: =+G35 -> 0.38 | H50: =+H35 -> 0.38
B51: liquidazione TFR | G51: -30 | H51: -30
A53: x | B53: Downsize Case
B54: revenues | D54: 0.09 | E54: 0.08 | F54: 0.07 | G54: -0.02 | H54: 0.03
B55: other incomes | D55: 0.06 | E55: 0.06 | F55: 0.08 | G55: 0.05 | H55: 0.05
B56: COGS | D56: 0.12 | E56: 0.12 | F56: 0.11 | G56: -0.03 | H56: 0.06
B57: salari | D57: 0.07 | E57: 0.07 | F57: 0.07 | G57: 0.03 | H57: 0.03
B58: oenri sociali | D58: 0.045 | E58: 0.045 | F58: 0.045 | G58: 0.045 | H58: 0.045
B59: accantonamento TFR | D59: 0.05 | E59: 0.05 | F59: 0.05 | G59: 0.05 | H59: 0.05
B60: tangibles assets | D60: 0.1 | E60: 0.1 | F60: 0.2 | G60: 0.2 | H60: 0.2
B61: itangibles assets | D61: 0.1 | E61: 0.1 | F61: 0.2 | G61: 0.2 | H61: 0.2
B62: proventi finanziari | D62: 30 | E62: 30 | F62: 30 | G62: 30 | H62: 30
B63: oneri finanziari | D63: =+D33 -> 120 | E63: =+E33 -> 120 | F63: =+F33 -> 120 | G63: =+G33 -> 120 | H63: =+H33 -> 120
B64: oneri gestione straordinaria | F64: -45
B65: tax rate | C65: =+C35 -> 0.38 | D65: =+D35 -> 0.38 | E65: =+E35 -> 0.38 | F65: =+F35 -> 0.38 | G65: =+G35 -> 0.38 | H65: =+H35 -> 0.38
B66: liquidazione TFR | G66: -30 | H66: -30
A69: x | B69: Income statement
B71: revenues | C71: 5000 | D71: =+C71*(1+D9) -> 5700 | E71: =+D71*(1+E9) -> 6498 | F71: =+E71*(1+F9) -> 7407.72 | G71: =+F71*(1+G9) -> 7333.6428 | H71: =+G71*(1+H9) -> 7920.3342
B72: other incomes | C72: 60 | D72: =+C72*(1+D10) -> 64.8 | E72: =+D72*(1+E10) -> 69.984 | F72: =+E72*(1+F10) -> 75.58272 | G72: =+F72*(1+G10) -> 79.361856 | H72: =+G72*(1+H10) -> 83.329949
B73: Total Revenues | C73: =SUM(C71:C72) -> 5060 | D73: =SUM(D71:D72) -> 5764.8 | E73: =SUM(E71:E72) -> 6567.984 | F73: =SUM(F71:F72) -> 7483.3027 | G73: =SUM(G71:G72) -> 7413.0047 | H73: =SUM(H71:H72) -> 8003.6642
B74: COGS | C74: 1400 | D74: =+C74*(1+D11) -> 1568 | E74: =+D74*(1+E11) -> 1740.48 | F74: =+E74*(1+F11) -> 1914.528 | G74: =+F74*(1+G11) -> 1857.0922 | H74: =+G74*(1+H11) -> 1949.9468
B75: Gross Margin | C75: =+C73-C74 -> 3660 | D75: =+D73-D74 -> 4196.8 | E75: =+E73-E74 -> 4827.504 | F75: =+F73-F74 -> 5568.7747 | G75: =+G73-G74 -> 5555.9125 | H75: =+H73-H74 -> 6053.7174
B76: Gross Margin% | C76: =+C75/$C$73 -> 0.72332016 | D76: =+D75/$D$73 -> 0.72800444 | E76: =+E75/$E$73 -> 0.73500544 | F76: =+F75/$F$73 -> 0.74416002 | G76: =+G75/$G$73 -> 0.74948186 | H76: =+H75/$H$73 -> 0.75636824
B77: SG&A
B78: salari | C78: 2000 | D78: =+C78*(1+D12) -> 2140 | E78: =+D78*(1+E12) -> 2289.8 | F78: =+E78*(1+F12) -> 2450.086 | G78: =+F78*(1+G12) -> 2523.5886 | H78: =+G78*(1+H12) -> 2599.2962
B79: oneri sociali | C79: 500 | D79: =+C79*(1+D13) -> 522.5 | E79: =+D79*(1+E13) -> 546.0125 | F79: =+E79*(1+F13) -> 570.58306 | G79: =+F79*(1+G13) -> 596.2593 | H79: =+G79*(1+H13) -> 623.09097
B80: accantonamento TFR | C80: 125 | D80: =+C80*(1+D14) -> 131.25 | E80: =+D80*(1+E14) -> 137.8125 | F80: =+E80*(1+F14) -> 144.70312 | G80: =+F80*(1+G14) -> 151.93828 | H80: =+G80*(1+H14) -> 159.5352
B81: Total SG&A | C81: =SUM(C78:C80) -> 2625 | D81: =SUM(D78:D80) -> 2793.75 | E81: =SUM(E78:E80) -> 2973.625 | F81: =SUM(F78:F80) -> 3165.3722 | G81: =SUM(G78:G80) -> 3271.7862 | H81: =SUM(H78:H80) -> 3381.9224
B82: EBITDA | C82: =+C75-C81 -> 1035 | D82: =+D75-D81 -> 1403.05 | E82: =+E75-E81 -> 1853.879 | F82: =+F75-F81 -> 2403.4025 | G82: =+G75-G81 -> 2284.1263 | H82: =+H75-H81 -> 2671.795
B83: EBITDA% | C83: =+C82/C73 -> 0.20454545 | D83: =+D82/D73 -> 0.24338225 | E83: =+E82/E73 -> 0.28225998 | F83: =+F82/F73 -> 0.32116869 | G83: =+G82/G73 -> 0.30812423 | H83: =+H82/H73 -> 0.33382148
B84: D&A
B85: tangibles | C85: 350 | D85: =+C85*(1+D15) -> 385 | E85: =+D85*(1+E15) -> 423.5 | F85: =+E85*(1+F15) -> 508.2 | G85: =+F85*(1+G15) -> 609.84 | H85: =+G85*(1+H15) -> 731.808
B86: intangibles | C86: 30 | D86: =+C86*(1+D16) -> 33 | E86: =+D86*(1+E16) -> 36.3 | F86: =+E86*(1+F16) -> 43.56 | G86: =+F86*(1+G16) -> 52.272 | H86: =+G86*(1+H16) -> 62.7264
B87: Total D&A | C87: =SUM(C85:C86) -> 380 | D87: =SUM(D85:D86) -> 418 | E87: =SUM(E85:E86) -> 459.8 | F87: =SUM(F85:F86) -> 551.76 | G87: =SUM(G85:G86) -> 662.112 | H87: =SUM(H85:H86) -> 794.5344
B88: EBIT | C88: =+C82-C87 -> 655 | D88: =+D82-D87 -> 985.05 | E88: =+E82-E87 -> 1394.079 | F88: =+F82-F87 -> 1851.6425 | G88: =+G82-G87 -> 1622.0143 | H88: =+H82-H87 -> 1877.2606
B89: EBIT% | C89: =+C88/C73 -> 0.12944664 | D89: =+D88/D73 -> 0.17087323 | E89: =+E88/E73 -> 0.21225371 | F89: =+F88/F73 -> 0.24743654 | G89: =+G88/G73 -> 0.2188066 | H89: =+H88/H73 -> 0.23455015
B90: proventi finanziari | C90: 20 | D90: =+D17 -> 30 | E90: =+E17 -> 30 | F90: =+F17 -> 30 | G90: =+G17 -> 30 | H90: =+H17 -> 30
B91: oneri finanziari | C91: 70 | D91: =+D18 -> 120 | E91: =+E18 -> 120 | F91: =+F18 -> 120 | G91: =+G18 -> 120 | H91: =+H18 -> 120
B92: Net financial interest | C92: =+C90-C91 -> -50 | D92: =+D90-D91 -> -90 | E92: =+E90-E91 -> -90 | F92: =+F90-F91 -> -90 | G92: =+G90-G91 -> -90 | H92: =+H90-H91 -> -90
B93: Gestione straordinaria | D93: =+D19 -> 0 | E93: =+E19 -> 0 | F93: =+F19 -> -45 | G93: =+G19 -> 0 | H93: =+H19 -> 0
B94: EBT | C94: =+C88+C92+C93 -> 605 | D94: =+D88+D92+D93 -> 895.05 | E94: =+E88+E92+E93 -> 1304.079 | F94: =+F88+F92+F93 -> 1716.6425 | G94: =+G88+G92+G93 -> 1532.0143 | H94: =+H88+H92+H93 -> 1787.2606
B95: EBT% | C95: =+C94/C73 -> 0.11956522 | D95: =+D94/D73 -> 0.15526124 | E95: =+E94/E73 -> 0.19855088 | F95: =+F94/F73 -> 0.22939638 | G95: =+G94/G73 -> 0.20666577 | H95: =+H94/H73 -> 0.2233053
B96: tax rate | C96: =+C94*C20 -> 229.9 | D96: =+D94*D20 -> 340.119 | E96: =+E94*E20 -> 495.55002 | F96: =+F94*F20 -> 652.32416 | G96: =+G94*G20 -> 582.16545 | H96: =+H94*H20 -> 679.15903
B97: Net Revenues | C97: =+C94-C96 -> 375.1 | D97: =+D94-D96 -> 554.931 | E97: =+E94-E96 -> 808.52898 | F97: =+F94-F96 -> 1064.3184 | G97: =+G94-G96 -> 949.84889 | H97: =+H94-H96 -> 1108.1016
B98: Net Revenues% | C98: =+C97/$C$73 -> 0.074130435 | D98: =+D97/D73 -> 0.096261969 | E98: =+E97/E73 -> 0.12310155 | F98: =+F97/F73 -> 0.14222575 | G98: =+G97/G73 -> 0.12813278 | H98: =+H97/H73 -> 0.13844928
A100: x | B100: Balance Sheet
B102: Attivo
B103: Cassa/Banca attiva | C103: 250 | D103: =+C103+D141 -> -930.819 | E103: =+D103+E141 -> -2998.1775 | F103: =+E103+F141 -> -3045.596 | G103: =+F103+G141 -> -1211.6969 | H103: =+G103+H141 -> 670.47431
B104: Crediti commerciali | C104: 1250 | D104: 2000 | E104: 2400 | F104: 2750 | G104: 3000 | H104: 3150
B105: Rimanenze | C105: 500 | D105: 650 | E105: 800 | F105: 950 | G105: 1100 | H105: 1100
B106: Tangibles assets | C106: 1400 | D106: 2800 | E106: 5500 | F106: 6500 | G106: 5890 | H106: 5158.352
B107: Intangibles assets | C107: 228 | D107: 195 | E107: 158.7 | F107: 115.14 | G107: 63 | H107: 0
B108: Imm.ni finanziarie | C108: 100 | D108: 100 | E108: 100 | F108: 100 | G108: 100 | H108: 100
B109: Totale Attivo | C109: =SUM(C103:C108) -> 3728 | D109: =SUM(D103:D108) -> 4814.181 | E109: =SUM(E103:E108) -> 5960.5225 | F109: =SUM(F103:F108) -> 7369.544 | G109: =SUM(G103:G108) -> 8941.3031 | H109: =SUM(H103:H108) -> 10178.826
B111: Passivo
B112: Debiti commerciali | C112: 1000 | D112: 1400 | E112: 1600 | F112: 1800 | G112: 2300 | H112: 2500
B113: Debiti verso banche | C113: 200 | D113: 200 | E113: 200 | F113: 200 | G113: 200 | H113: 0
...

Sheet EV_EqV
E3: Forecast Periods
B4: Voce (€ milioni) | C4: 1 | D4: =+C4+1 -> 2 | E4: =+D4+1 -> 3 | F4: =+E4+1 -> 4 | G4: =+F4+1 -> 5
A6: x | B6: Project Valuation
B8: uFCFF | C8: =+'3_statement_model'!D135 -> -1090.819 | D8: =+'3_statement_model'!E135 -> -1977.3585 | E8: =+'3_statement_model'!F135 -> 87.581495 | F8: =+'3_statement_model'!G135 -> 1923.8992 | G8: =+'3_statement_model'!H135 -> 2172.1712
B9: uDCF | C9: =+C8/(1+$C$42)^C4 -> -1016.0504 | D9: =+D8/(1+$C$42)^D4 -> -1715.5782 | E9: =+E8/(1+$C$42)^E4 -> 70.778282 | F9: =+F8/(1+$C$42)^F4 -> 1448.2133 | G9: =+G8/(1+$C$42)^G4 -> 1523.0242
B10: TV | G10: =+(+'3_statement_model'!H127)*(1+$C$30)/(C42-C30) -> 22805.012
B12: PFN | E12: Enterprise Value
B13: (+) financial debts | C13: =+'3_statement_model'!C113 -> 200 | E13: (+) NPV CF | F13: =+SUM(C9:G9) -> 310.38716
B14: (-) liquidity | C14: =-'3_statement_model'!C103 -> -250 | E14: (+) NPV TV | F14: =+G10/(1+$C$42)^G4 -> 15989.802
B15: PFN | C15: =SUM(C13:C14) -> -50 | E15: EV | F15: =SUM(F13:F14) -> 16300.189
E17: Equity Value
E18: (+) EV | F18: =+F15 -> 16300.189
E19: (-) PFN | F19: =-C15 -> 50
E20: EqV | F20: =SUM(F18:F19) -> 16350.189
A23: x | B23: Dati
B25: risk-free | C25: 0.035
B26: return-market | C26: 0.055
B27: B | C27: 1.2
B28: cost of debt | C28: 0.045
B29: leva finanziaria | C29: 0.6
B30: tasso crescita (g) | C30: 0.02
B31: Tax-Rate | C31: =+'3_statement_model'!C20 -> 0.38
B33: WACC
B35: D | C35: 0.6 | D35: =+C35/$C$37 -> 0.375 | E35: Kd | F35: =+C28*(1-C31) -> 0.0279
B36: E | C36: 1 | D36: =+C36/$C$37 -> 0.625 | E36: Ke | F36: =+C25+C27*(C26) -> 0.101
B37: Total | C37: =SUM(C35:C36) -> 1.6 | D37: =+C37/$C$37 -> 1
B38: leverage | C38: 0.6
B40: D weighted | C40: =+D35*F35 -> 0.0104625
B41: E weighted | C41: =+D36*F36 -> 0.063125
B42: WACC | C42: =SUM(C40:C41) -> 0.0735875
